{
  "parent": "minecraft:recipes/root",
  "rewards": {
    "recipes": [
      "lightestlamp:neon_rod_block"
    ]
  },
  "criteria": {
    "netherrack": {
      "trigger": "minecraft:inventory_changed",
      "conditions": {
        "items": [
          {
            "item": "minecraft:netherrack"
          }
        ]
      }
    },
    "has_the_recipe": {
      "trigger": "minecraft:recipe_unlocked",
      "conditions": {
        "recipe": "lightestlamp:neon_rod_block"
      }
    }
  },
  "requirements": [
    [
      "netherrack",
      "has_the_recipe"
    ]
  ]
}